{"otherData": {},"traceEvents":[{"cat":"function","dur":604868,"name":"glfwInit","ph":"X","pid":0,"tid":91442370,"ts":1777695586544},{"cat":"function","dur":255248,"name":"glfwCreateWindow","ph":"X","pid":0,"tid":91442370,"ts":1777696191679},{"cat":"function","dur":3558,"name":"void __cdecl Chimera::OpenGLContext::Init(void)","ph":"X","pid":0,"tid":91442370,"ts":1777696447074},{"cat":"function","dur":36,"name":"void __cdecl Chimera::WindowsWindow::SetVSync(bool)","ph":"X","pid":0,"tid":91442370,"ts":1777696450745},{"cat":"function","dur":865646,"name":"void __cdecl Chimera::WindowsWindow::Init(const struct Chimera::WindowProps &)","ph":"X","pid":0,"tid":91442370,"ts":1777695585212},{"cat":"function","dur":865702,"name":"__cdecl Chimera::WindowsWindow::WindowsWindow(const struct Chimera::WindowProps &)","ph":"X","pid":0,"tid":91442370,"ts":1777695585208},{"cat":"function","dur":6,"name":"void __cdecl Chimera::OpenGLRendererAPI::Init(void)","ph":"X","pid":0,"tid":91442370,"ts":1777696451002},{"cat":"function","dur":58,"name":"void __cdecl Chimera::RenderCommand::Init(void)","ph":"X","pid":0,"tid":91442370,"ts":1777696451001},{"cat":"function","dur":23,"name":"__cdecl Chimera::OpenGLVertexArray::OpenGLVertexArray(void)","ph":"X","pid":0,"tid":91442370,"ts":1777696451145},{"cat":"function","dur":103,"name":"class std::shared_ptr<class Chimera::VertexArray> __cdecl Chimera::VertexArray::Create(void)","ph":"X","pid":0,"tid":91442370,"ts":1777696451121},{"cat":"function","dur":13,"name":"__cdecl Chimera::OpenGLVertexBuffer::OpenGLVertexBuffer(unsigned int)","ph":"X","pid":0,"tid":91442370,"ts":1777696451308},{"cat":"function","dur":0,"name":"void __cdecl Chimera::OpenGLVertexBuffer::Bind(void) const","ph":"X","pid":0,"tid":91442370,"ts":1777696451493},{"cat":"function","dur":125,"name":"void __cdecl Chimera::OpenGLVertexArray::AddVertexBuffer(const class std::shared_ptr<class Chimera::VertexBuffer> &)","ph":"X","pid":0,"tid":91442370,"ts":1777696451447},{"cat":"function","dur":77,"name":"__cdecl Chimera::OpenGLIndexBuffer::OpenGLIndexBuffer(unsigned int *,unsigned int)","ph":"X","pid":0,"tid":91442370,"ts":1777696452229},{"cat":"function","dur":0,"name":"void __cdecl Chimera::OpenGLIndexBuffer::Bind(void) const","ph":"X","pid":0,"tid":91442370,"ts":1777696452362},{"cat":"function","dur":61,"name":"void __cdecl Chimera::OpenGLVertexArray::SetIndexBuffer(const class std::shared_ptr<class Chimera::IndexBuffer> &)","ph":"X","pid":0,"tid":91442370,"ts":1777696452361},{"cat":"function","dur":494,"name":"__cdecl Chimera::OpenGLTexture2D::OpenGLTexture2D(unsigned int,unsigned int)","ph":"X","pid":0,"tid":91442370,"ts":1777696452515},{"cat":"function","dur":9,"name":"void __cdecl Chimera::OpenGLTexture2D::SetData(void *,unsigned int)","ph":"X","pid":0,"tid":91442370,"ts":1777696453077},{"cat":"function","dur":273,"name":"class std::basic_string<char,struct std::char_traits<char>,class std::allocator<char> > __cdecl Chimera::OpenGLShader::ReadFile(const class std::basic_string<char,struct std::char_traits<char>,class std::allocator<char> > &)","ph":"X","pid":0,"tid":91442370,"ts":1777696453160},{"cat":"function","dur":93,"name":"class std::unordered_map<unsigned int,class std::basic_string<char,struct std::char_traits<char>,class std::allocator<char> >,struct std::hash<unsigned int>,struct std::equal_to<unsigned int>,class std::allocator<struct std::pair<unsigned int const ,class std::basic_string<char,struct std::char_traits<char>,class std::allocator<char> > > > > __cdecl Chimera::OpenGLShader::PreProcess(const class std::basic_string<char,struct std::char_traits<char>,class std::allocator<char> > &)","ph":"X","pid":0,"tid":91442370,"ts":1777696453515},{"cat":"function","dur":1095,"name":"void __cdecl Chimera::OpenGLShader::Compile(const class std::unordered_map<unsigned int,class std::basic_string<char,struct std::char_traits<char>,class std::allocator<char> >,struct std::hash<unsigned int>,struct std::equal_to<unsigned int>,class std::allocator<struct std::pair<unsigned int const ,class std::basic_string<char,struct std::char_traits<char>,class std::allocator<char> > > > > &)","ph":"X","pid":0,"tid":91442370,"ts":1777696453665},{"cat":"function","dur":1818,"name":"__cdecl Chimera::OpenGLShader::OpenGLShader(const class std::basic_string<char,struct std::char_traits<char>,class std::allocator<char> > &)","ph":"X","pid":0,"tid":91442370,"ts":1777696453157},{"cat":"function","dur":2,"name":"void __cdecl Chimera::OpenGLShader::Bind(void) const","ph":"X","pid":0,"tid":91442370,"ts":1777696455060},{"cat":"function","dur":4062,"name":"void __cdecl Chimera::Renderer2D::Init(void)","ph":"X","pid":0,"tid":91442370,"ts":1777696451117},{"cat":"function","dur":4268,"name":"void __cdecl Chimera::Renderer::Init(void)","ph":"X","pid":0,"tid":91442370,"ts":1777696451001},{"cat":"function","dur":1114,"name":"void __cdecl Chimera::ImGuiLayer::OnAttach(void)","ph":"X","pid":0,"tid":91442370,"ts":1777696455348},{"cat":"function","dur":1200,"name":"void __cdecl Chimera::Application::PushOverlay(class Chimera::Layer *)","ph":"X","pid":0,"tid":91442370,"ts":1777696455331},{"cat":"function","dur":871402,"name":"__cdecl Chimera::Application::Application(const class std::basic_string<char,struct std::char_traits<char>,class std::allocator<char> > &)","ph":"X","pid":0,"tid":91442370,"ts":1777695585180},{"cat":"function","dur":7,"name":"__cdecl Chimera::OrthographicCamera::OrthographicCamera(float,float,float,float)","ph":"X","pid":0,"tid":91442370,"ts":1777696456654},{"cat":"function","dur":2346,"name":"void __cdecl Chimera::EditorLayer::OnAttach(void)","ph":"X","pid":0,"tid":91442370,"ts":1777696456729},{"cat":"function","dur":2438,"name":"void __cdecl Chimera::Application::PushLayer(class Chimera::Layer *)","ph":"X","pid":0,"tid":91442370,"ts":1777696456717}]}